[
  {
    "videoId": "e0MdYPY4te0",
    "title": "😱 We Highly Recommend This Intense Thriller That Will Take Your Breath Away! Watch For Free",
    "channel": "FILMDOMINION",
    "thumbnail": "https://i.ytimg.com/vi/e0MdYPY4te0/hqdefault.jpg"
  },
  {
    "videoId": "8Ser7R8PUy8",
    "title": "This Film’s Story Deserves an Oscar! Watch This Thriller Free | Full Movie",
    "channel": "FilmVaultX",
    "thumbnail": "https://i.ytimg.com/vi/8Ser7R8PUy8/hqdefault.jpg"
  },
  {
    "videoId": "xZieytGan9o",
    "title": "🎬This Thriller Shocks from the First Minutes! | Watch Full Movie Free",
    "channel": "FILMDOMINION",
    "thumbnail": "https://i.ytimg.com/vi/xZieytGan9o/hqdefault.jpg"
  },
  {
    "videoId": "ZgBREuq7XyU",
    "title": "Quick FULL MOVIE | Thriller Movie | Teri Polo &amp; Martin Donovan | Femme Fatales",
    "channel": "Femme Fatales",
    "thumbnail": "https://i.ytimg.com/vi/ZgBREuq7XyU/hqdefault.jpg"
  },
  {
    "videoId": "0YrxiyAl18M",
    "title": "The White Orchid | English Full Movie | Drama Mystery Thriller",
    "channel": "GEM: Film Library",
    "thumbnail": "https://i.ytimg.com/vi/0YrxiyAl18M/hqdefault.jpg"
  },
  {
    "videoId": "e4aZpA2x7cQ",
    "title": "🎬 A psychological thriller you can’t look away from! | THE PERCEPTION | English Full Movie",
    "channel": "MOVIETOWN media",
    "thumbnail": "https://i.ytimg.com/vi/e4aZpA2x7cQ/hqdefault.jpg"
  },
  {
    "videoId": "BCVi0ZshzAE",
    "title": "She Admitted the Crime… But the Evidence Doesn’t Match! | Thriller | Full Movie 4K",
    "channel": "TimeLensTV",
    "thumbnail": "https://i.ytimg.com/vi/BCVi0ZshzAE/hqdefault.jpg"
  },
  {
    "videoId": "3h51ZuMU5pc",
    "title": "A crime thriller movie based on true events that will keep you guessing until the final minute!",
    "channel": "FBX Films",
    "thumbnail": "https://i.ytimg.com/vi/3h51ZuMU5pc/hqdefault.jpg"
  },
  {
    "videoId": "Pni-szLcHwA",
    "title": "FATAL INSTINCT | Full-Length Crime Thriller | Serial Killer Mystery Film | Watch Full HD 🕵️‍♂️",
    "channel": "Dzango Movies – Heavy on Action. Light on Drama.",
    "thumbnail": "https://i.ytimg.com/vi/Pni-szLcHwA/hqdefault.jpg"
  },
  {
    "videoId": "Z4PmKwpWTgc",
    "title": "Top 7 best suspense thriller movies&quot;Best Hollywood Thriller Movies #thrillermovies #netflix",
    "channel": "Cine Vault ",
    "thumbnail": "https://i.ytimg.com/vi/Z4PmKwpWTgc/hqdefault.jpg"
  },
  {
    "videoId": "thoGWMmw7Fk",
    "title": "TRUST NO ONE 🎬  Full Thriller Movie 🎬 English HD",
    "channel": "FullFlicks Central",
    "thumbnail": "https://i.ytimg.com/vi/thoGWMmw7Fk/hqdefault.jpg"
  },
  {
    "videoId": "bJMj-5zvZJQ",
    "title": "Persons Unknown FULL MOVIE | Thriller Movie | Kelly Lynch &amp; Naomi Watts | Femme Fatales",
    "channel": "Femme Fatales",
    "thumbnail": "https://i.ytimg.com/vi/bJMj-5zvZJQ/hqdefault.jpg"
  },
  {
    "videoId": "TSeRNTPl07Y",
    "title": "A Powerful Shocking Thriller With A Shocking Ending | Full Movie in English",
    "channel": "CineStrike",
    "thumbnail": "https://i.ytimg.com/vi/TSeRNTPl07Y/hqdefault.jpg"
  },
  {
    "videoId": "DpCSHMQzluM",
    "title": "HER DEADLY REFLECTIONS | Full Thriller Movie | Helena Mattsson, Corey Sevier, Melanie Stone",
    "channel": "The Cinematics Stories",
    "thumbnail": "https://i.ytimg.com/vi/DpCSHMQzluM/hqdefault.jpg"
  },
  {
    "videoId": "PirkQXsrjas",
    "title": "One of the Most Disturbing Thriller Movies Viewers Have Ever Seen | Full Movies in English",
    "channel": "Epic Movie Nexus",
    "thumbnail": "https://i.ytimg.com/vi/PirkQXsrjas/hqdefault.jpg"
  },
  {
    "videoId": "SLubR4PiFys",
    "title": "They Hunted Her, Now She’s Hunting Them | Action Thriller | Full Movie in English",
    "channel": "KaleidoScreen",
    "thumbnail": "https://i.ytimg.com/vi/SLubR4PiFys/hqdefault.jpg"
  },
  {
    "videoId": "tT6pL-kzuVc",
    "title": "Powerful movie based on a True Story! | Crime, Thriller | Full Movies",
    "channel": "Filmaxia",
    "thumbnail": "https://i.ytimg.com/vi/tT6pL-kzuVc/hqdefault.jpg"
  },
  {
    "videoId": "c2YBgDFNC9c",
    "title": "Criminals New Action English Hollywood Movie | Hollywood Blockbuster Action Thriller Movie 2026",
    "channel": " Roy Cinema",
    "thumbnail": "https://i.ytimg.com/vi/c2YBgDFNC9c/hqdefault.jpg"
  },
  {
    "videoId": "Ii-dBclZijY",
    "title": "😱 A Thriller That Will Keep You On Edge Until The Very Last Second! Watch Online",
    "channel": "FILMDOMINION",
    "thumbnail": "https://i.ytimg.com/vi/Ii-dBclZijY/hqdefault.jpg"
  },
  {
    "videoId": "jK4ekMKL7Og",
    "title": "The Girl FULL MOVIE | Michael Biehn &amp; Tia Carrere | Thriller Movie | Femme Fatales",
    "channel": "Femme Fatales",
    "thumbnail": "https://i.ytimg.com/vi/jK4ekMKL7Og/hqdefault.jpg"
  },
  {
    "videoId": "ZatGZ9d_LNE",
    "title": "Professional Killer | HD | Thriller | Full Movie in English",
    "channel": "Infinite English Movies",
    "thumbnail": "https://i.ytimg.com/vi/ZatGZ9d_LNE/hqdefault.jpg"
  },
  {
    "videoId": "4CIW_fjb3Z0",
    "title": "Preys In The Night | THRILLER | Full Movie in English",
    "channel": "Full Movies in English HD",
    "thumbnail": "https://i.ytimg.com/vi/4CIW_fjb3Z0/hqdefault.jpg"
  },
  {
    "videoId": "oBhen3NXMRc",
    "title": "Survival Knows No Boundaries | No Escape | Full Action Thriller Movie | Free Movie",
    "channel": "V Movies",
    "thumbnail": "https://i.ytimg.com/vi/oBhen3NXMRc/hqdefault.jpg"
  },
  {
    "videoId": "PyzccmGpn2I",
    "title": "After Alice FULL MOVIE | Kiefer Sutherland | Thriller Movies | The Midnight Screening",
    "channel": "The Midnight Screening",
    "thumbnail": "https://i.ytimg.com/vi/PyzccmGpn2I/hqdefault.jpg"
  },
  {
    "videoId": "4wihbYopspQ",
    "title": "Pursued (2025) | Full Movie | Thriller | Horror | Madison Lawlor | Sam Trammell | Molly Ringwald",
    "channel": "Indie Rights Movies For Free",
    "thumbnail": "https://i.ytimg.com/vi/4wihbYopspQ/hqdefault.jpg"
  },
  {
    "videoId": "_FSp26YoFbw",
    "title": "IT&#39;S A MOVIE YOU&#39;LL WANT TO WATCH AGAIN AND AGAIN! | Action, Crime Movies in English | HD",
    "channel": "MOOVIMIND",
    "thumbnail": "https://i.ytimg.com/vi/_FSp26YoFbw/hqdefault.jpg"
  },
  {
    "videoId": "D_FX3vbk5oM",
    "title": "Ryan Gosling In THE DISAPPEARANCE - Hollywood Mystery Thriller Full Movie In English | Kristen Dunst",
    "channel": "Blockbuster English Movies",
    "thumbnail": "https://i.ytimg.com/vi/D_FX3vbk5oM/hqdefault.jpg"
  },
  {
    "videoId": "DGjOUNIU4rY",
    "title": "A Gripping Detective Thriller You’ll Remember Long After It Ends | Full Movie",
    "channel": "Movies Anytime",
    "thumbnail": "https://i.ytimg.com/vi/DGjOUNIU4rY/hqdefault.jpg"
  },
  {
    "videoId": "CkIkgsiE3Rs",
    "title": "Full Crime Revenge Thriller | Hit-men are sent to silence them… big mistake | Action Movies",
    "channel": "More Movies in English",
    "thumbnail": "https://i.ytimg.com/vi/CkIkgsiE3Rs/hqdefault.jpg"
  },
  {
    "videoId": "37mDWZJXuuY",
    "title": "Liam Neeson In TAKEN IDENTITY - Hollywood Movie | Superhit Action Thriller Full Movie In English HD",
    "channel": "Blockbuster English Movies",
    "thumbnail": "https://i.ytimg.com/vi/37mDWZJXuuY/hqdefault.jpg"
  },
  {
    "videoId": "MtL4q6I7KXg",
    "title": "The Last Call… 2026 | A Thriller Movies 2026 New Releases | Based On True Story",
    "channel": "ReelMystery",
    "thumbnail": "https://i.ytimg.com/vi/MtL4q6I7KXg/hqdefault.jpg"
  },
  {
    "videoId": "TkJU90FSh4M",
    "title": "Recommended to Watch! She Entered His Life for Revenge | The Perfect Wife - Full Movie in English",
    "channel": "FILMZION",
    "thumbnail": "https://i.ytimg.com/vi/TkJU90FSh4M/hqdefault.jpg"
  },
  {
    "videoId": "4lKLeL1gXj4",
    "title": "Hide | Full Movie | Detective Crime Thriller Movie | Six Mummified Bodies Found",
    "channel": "Movie Central",
    "thumbnail": "https://i.ytimg.com/vi/4lKLeL1gXj4/hqdefault.jpg"
  },
  {
    "videoId": "7826nZGrF40",
    "title": "A crime thriller movie based on true events that keeps you in suspense until the end!",
    "channel": "Actionmovie pictures",
    "thumbnail": "https://i.ytimg.com/vi/7826nZGrF40/hqdefault.jpg"
  },
  {
    "videoId": "w9TZCX9fZ1A",
    "title": "OUTLAWED | THRILLER | Full Movie in English",
    "channel": "Boxoffice | NEW Full Movies in English",
    "thumbnail": "https://i.ytimg.com/vi/w9TZCX9fZ1A/hqdefault.jpg"
  },
  {
    "videoId": "bOGgDOKtgBA",
    "title": "HOUSE ON ROCKINGHAM 🎬 Full Thriller Movie 🎬 English HD",
    "channel": "WATCH THRILLER MOVIES NOW",
    "thumbnail": "https://i.ytimg.com/vi/bOGgDOKtgBA/hqdefault.jpg"
  },
  {
    "videoId": "tTkjL_dt5hA",
    "title": "The Forgotten Village FULL MOVIE | Thriller Movie | Susan Hoecke Mike Hoffmann | Femme Fatales",
    "channel": "Femme Fatales",
    "thumbnail": "https://i.ytimg.com/vi/tTkjL_dt5hA/hqdefault.jpg"
  },
  {
    "videoId": "T13stc_xFkw",
    "title": "She’s Trapped in the Desert! | Thriller movie | Hangar | Full movies",
    "channel": "MOVIEBAND production",
    "thumbnail": "https://i.ytimg.com/vi/T13stc_xFkw/hqdefault.jpg"
  },
  {
    "videoId": "Ulns8C2bp8U",
    "title": "I Witness FULL MOVIE | James Spader &amp; Jeff Daniels | Action Movies | The Midnight Screening",
    "channel": "The Midnight Screening",
    "thumbnail": "https://i.ytimg.com/vi/Ulns8C2bp8U/hqdefault.jpg"
  },
  {
    "videoId": "luqEJxOXEyQ",
    "title": "Top 5 Netflix Suspense Thriller Movies.#thriller #movies #netflix #top #best #hollywood #mostwatched",
    "channel": "FunMarvel",
    "thumbnail": "https://i.ytimg.com/vi/luqEJxOXEyQ/hqdefault.jpg"
  },
  {
    "videoId": "hcNcZaPNoP0",
    "title": "ROOM FOR RENT | Full Horror Thriller Movie | Lin Shaye, Oliver Rayon, Ryan Ochoa",
    "channel": "The Cinematics Frights",
    "thumbnail": "https://i.ytimg.com/vi/hcNcZaPNoP0/hqdefault.jpg"
  },
  {
    "videoId": "yRN7yfzZS2A",
    "title": "MALICIOUS | Full Psychological Thriller Movie | Molly Ringwald, John Vernon, Patrick McGaw",
    "channel": "The Cinematics Movies",
    "thumbnail": "https://i.ytimg.com/vi/yRN7yfzZS2A/hqdefault.jpg"
  },
  {
    "videoId": "lO2a60PSe5o",
    "title": "Metro (2013) FULL MOVIE | Epic Disaster Thriller",
    "channel": "Free Movies By CONtv",
    "thumbnail": "https://i.ytimg.com/vi/lO2a60PSe5o/hqdefault.jpg"
  },
  {
    "videoId": "CkzTDXqwhZg",
    "title": "Double murder | Drama Thriller| Full Movie in English",
    "channel": "Top Screen",
    "thumbnail": "https://i.ytimg.com/vi/CkzTDXqwhZg/hqdefault.jpg"
  },
  {
    "videoId": "iI3MxONFtYI",
    "title": "A Shocking Survival Story! | SNAKE CREEK | Full Movie in English",
    "channel": "Dark Frame",
    "thumbnail": "https://i.ytimg.com/vi/iI3MxONFtYI/hqdefault.jpg"
  },
  {
    "videoId": "Nzns-smWV8Y",
    "title": "A Thriller That Won&#39;t Let Go | The Murder Mystery That Ruined Everything 🎬 A Clean Kill Movie",
    "channel": "Movexia",
    "thumbnail": "https://i.ytimg.com/vi/Nzns-smWV8Y/hqdefault.jpg"
  },
  {
    "videoId": "1r1q4p-QLqQ",
    "title": "Crime Action Movie | The Killer Who Lost Control! | Full Movie in English",
    "channel": "Movie union",
    "thumbnail": "https://i.ytimg.com/vi/1r1q4p-QLqQ/hqdefault.jpg"
  },
  {
    "videoId": "eLuidLxeQeU",
    "title": "When the Price of Escape Is Too High | Crime Thriller in English",
    "channel": "Film Customs",
    "thumbnail": "https://i.ytimg.com/vi/eLuidLxeQeU/hqdefault.jpg"
  },
  {
    "videoId": "L6FBrfgdo9Y",
    "title": "A Remote Tower Deep in the Forest Hides Something Terrifying | THRILLER | Free English Movies in 4K",
    "channel": "MovieThreeX",
    "thumbnail": "https://i.ytimg.com/vi/L6FBrfgdo9Y/hqdefault.jpg"
  },
  {
    "videoId": "SE7C8E0EC74",
    "title": "END OF THE WORLD: 2026 | Full Movie | English | Disaster | Thriller | 4K",
    "channel": "Epic AI Films",
    "thumbnail": "https://i.ytimg.com/vi/SE7C8E0EC74/hqdefault.jpg"
  }
]