{
  "timestamp": 1780491436958,
  "photos": [
    {
      "id": "55302545391",
      "owner": "143307536@N06",
      "secret": "352588e1fe",
      "server": "65535",
      "farm": 66,
      "title": "come with me",
      "ispublic": 1,
      "isfriend": 0,
      "isfamily": 0
    },
    {
      "id": "55301022670",
      "owner": "143307536@N06",
      "secret": "f7e2573e19",
      "server": "65535",
      "farm": 66,
      "title": "metal face",
      "ispublic": 1,
      "isfriend": 0,
      "isfamily": 0
    },
    {
      "id": "55298520521",
      "owner": "143307536@N06",
      "secret": "ba72f674cb",
      "server": "65535",
      "farm": 66,
      "title": "tentacles",
      "ispublic": 1,
      "isfriend": 0,
      "isfamily": 0
    },
    {
      "id": "55295562117",
      "owner": "143307536@N06",
      "secret": "41c0bb2f8a",
      "server": "65535",
      "farm": 66,
      "title": "desperate",
      "ispublic": 1,
      "isfriend": 0,
      "isfamily": 0
    },
    {
      "id": "55294161488",
      "owner": "143307536@N06",
      "secret": "e4200de410",
      "server": "65535",
      "farm": 66,
      "title": "Woman",
      "ispublic": 1,
      "isfriend": 0,
      "isfamily": 0
    },
    {
      "id": "55291688666",
      "owner": "143307536@N06",
      "secret": "0e193270c0",
      "server": "65535",
      "farm": 66,
      "title": "Palace",
      "ispublic": 1,
      "isfriend": 0,
      "isfamily": 0
    },
    {
      "id": "55291909299",
      "owner": "143307536@N06",
      "secret": "c197e08d4a",
      "server": "65535",
      "farm": 66,
      "title": "Lupa",
      "ispublic": 1,
      "isfriend": 0,
      "isfamily": 0
    },
    {
      "id": "55290327105",
      "owner": "143307536@N06",
      "secret": "b66426bb1c",
      "server": "65535",
      "farm": 66,
      "title": "comics",
      "ispublic": 1,
      "isfriend": 0,
      "isfamily": 0
    },
    {
      "id": "55290184435",
      "owner": "143307536@N06",
      "secret": "6ac2d2af1f",
      "server": "65535",
      "farm": 66,
      "title": "Chain",
      "ispublic": 1,
      "isfriend": 0,
      "isfamily": 0
    },
    {
      "id": "55287915531",
      "owner": "143307536@N06",
      "secret": "d6e4b7e7c4",
      "server": "65535",
      "farm": 66,
      "title": "Il saluto",
      "ispublic": 1,
      "isfriend": 0,
      "isfamily": 0
    },
    {
      "id": "55288022693",
      "owner": "143307536@N06",
      "secret": "4d0be1a4e0",
      "server": "65535",
      "farm": 66,
      "title": "prisoner",
      "ispublic": 1,
      "isfriend": 0,
      "isfamily": 0
    },
    {
      "id": "55286175944",
      "owner": "143307536@N06",
      "secret": "b4a8883312",
      "server": "65535",
      "farm": 66,
      "title": "blade runner",
      "ispublic": 1,
      "isfriend": 0,
      "isfamily": 0
    },
    {
      "id": "55286157749",
      "owner": "143307536@N06",
      "secret": "0bb85e342c",
      "server": "65535",
      "farm": 66,
      "title": "Alien invasion",
      "ispublic": 1,
      "isfriend": 0,
      "isfamily": 0
    },
    {
      "id": "55284088998",
      "owner": "143307536@N06",
      "secret": "5fa61b01ab",
      "server": "65535",
      "farm": 66,
      "title": "tongue",
      "ispublic": 1,
      "isfriend": 0,
      "isfamily": 0
    },
    {
      "id": "55282477793",
      "owner": "143307536@N06",
      "secret": "714c99d877",
      "server": "65535",
      "farm": 66,
      "title": "Django",
      "ispublic": 1,
      "isfriend": 0,
      "isfamily": 0
    },
    {
      "id": "55281976111",
      "owner": "143307536@N06",
      "secret": "3142cb44f9",
      "server": "65535",
      "farm": 66,
      "title": "woman",
      "ispublic": 1,
      "isfriend": 0,
      "isfamily": 0
    },
    {
      "id": "55279794432",
      "owner": "143307536@N06",
      "secret": "c6b067d716",
      "server": "65535",
      "farm": 66,
      "title": "white queen",
      "ispublic": 1,
      "isfriend": 0,
      "isfamily": 0
    },
    {
      "id": "55280023081",
      "owner": "143307536@N06",
      "secret": "5fa12ae3f0",
      "server": "65535",
      "farm": 66,
      "title": "Taurus",
      "ispublic": 1,
      "isfriend": 0,
      "isfamily": 0
    },
    {
      "id": "55280415135",
      "owner": "143307536@N06",
      "secret": "fba3621636",
      "server": "65535",
      "farm": 66,
      "title": "Red horse",
      "ispublic": 1,
      "isfriend": 0,
      "isfamily": 0
    },
    {
      "id": "55252278688",
      "owner": "143307536@N06",
      "secret": "61815eaf6f",
      "server": "65535",
      "farm": 66,
      "title": "Silk",
      "ispublic": 1,
      "isfriend": 0,
      "isfamily": 0
    },
    {
      "id": "55250067421",
      "owner": "143307536@N06",
      "secret": "5fca5c67e0",
      "server": "65535",
      "farm": 66,
      "title": "Humanoid",
      "ispublic": 1,
      "isfriend": 0,
      "isfamily": 0
    },
    {
      "id": "55248748824",
      "owner": "143307536@N06",
      "secret": "5b1d26211a",
      "server": "65535",
      "farm": 66,
      "title": "Executioner",
      "ispublic": 1,
      "isfriend": 0,
      "isfamily": 0
    },
    {
      "id": "55244028905",
      "owner": "143307536@N06",
      "secret": "e5409f0fb6",
      "server": "65535",
      "farm": 66,
      "title": "Baboom",
      "ispublic": 1,
      "isfriend": 0,
      "isfamily": 0
    },
    {
      "id": "55241916913",
      "owner": "143307536@N06",
      "secret": "6209594aab",
      "server": "65535",
      "farm": 66,
      "title": "Abstract kiss",
      "ispublic": 1,
      "isfriend": 0,
      "isfamily": 0
    },
    {
      "id": "55242002810",
      "owner": "143307536@N06",
      "secret": "2f75591bcd",
      "server": "65535",
      "farm": 66,
      "title": "rust",
      "ispublic": 1,
      "isfriend": 0,
      "isfamily": 0
    },
    {
      "id": "55239935361",
      "owner": "143307536@N06",
      "secret": "2a7aa9c598",
      "server": "65535",
      "farm": 66,
      "title": "the bubble",
      "ispublic": 1,
      "isfriend": 0,
      "isfamily": 0
    },
    {
      "id": "55238500405",
      "owner": "143307536@N06",
      "secret": "791fb0aa27",
      "server": "65535",
      "farm": 66,
      "title": "Sphere",
      "ispublic": 1,
      "isfriend": 0,
      "isfamily": 0
    },
    {
      "id": "55235285322",
      "owner": "143307536@N06",
      "secret": "725355f997",
      "server": "65535",
      "farm": 66,
      "title": "in Cross",
      "ispublic": 1,
      "isfriend": 0,
      "isfamily": 0
    },
    {
      "id": "55233799471",
      "owner": "143307536@N06",
      "secret": "166aa42c81",
      "server": "65535",
      "farm": 66,
      "title": "Alexia",
      "ispublic": 1,
      "isfriend": 0,
      "isfamily": 0
    },
    {
      "id": "55195582902",
      "owner": "143307536@N06",
      "secret": "1ec16a2f73",
      "server": "65535",
      "farm": 66,
      "title": "Snakes",
      "ispublic": 1,
      "isfriend": 0,
      "isfamily": 0
    },
    {
      "id": "55195399057",
      "owner": "143307536@N06",
      "secret": "72f9d348e3",
      "server": "65535",
      "farm": 66,
      "title": "Sushi ?",
      "ispublic": 1,
      "isfriend": 0,
      "isfamily": 0
    },
    {
      "id": "55194538521",
      "owner": "143307536@N06",
      "secret": "af089681dc",
      "server": "65535",
      "farm": 66,
      "title": "the eyes",
      "ispublic": 1,
      "isfriend": 0,
      "isfamily": 0
    },
    {
      "id": "55194913230",
      "owner": "143307536@N06",
      "secret": "8649a057ea",
      "server": "65535",
      "farm": 66,
      "title": "Sadness",
      "ispublic": 1,
      "isfriend": 0,
      "isfamily": 0
    },
    {
      "id": "55191740747",
      "owner": "143307536@N06",
      "secret": "5d7065235c",
      "server": "65535",
      "farm": 66,
      "title": "Valkyrie",
      "ispublic": 1,
      "isfriend": 0,
      "isfamily": 0
    },
    {
      "id": "55192700718",
      "owner": "143307536@N06",
      "secret": "07cd527bdc",
      "server": "65535",
      "farm": 66,
      "title": "Crab",
      "ispublic": 1,
      "isfriend": 0,
      "isfamily": 0
    },
    {
      "id": "55190460031",
      "owner": "143307536@N06",
      "secret": "c2cb18b34b",
      "server": "65535",
      "farm": 66,
      "title": "Bleah",
      "ispublic": 1,
      "isfriend": 0,
      "isfamily": 0
    },
    {
      "id": "55188126532",
      "owner": "143307536@N06",
      "secret": "19a3b92e3c",
      "server": "65535",
      "farm": 66,
      "title": "Cannibals ?",
      "ispublic": 1,
      "isfriend": 0,
      "isfamily": 0
    },
    {
      "id": "55187665147",
      "owner": "143307536@N06",
      "secret": "53472f4e6b",
      "server": "65535",
      "farm": 66,
      "title": "A kiss",
      "ispublic": 1,
      "isfriend": 0,
      "isfamily": 0
    },
    {
      "id": "55185882092",
      "owner": "143307536@N06",
      "secret": "78140c0e19",
      "server": "65535",
      "farm": 66,
      "title": "The construction site",
      "ispublic": 1,
      "isfriend": 0,
      "isfamily": 0
    },
    {
      "id": "55186763978",
      "owner": "143307536@N06",
      "secret": "40b1fcda5c",
      "server": "65535",
      "farm": 66,
      "title": "In chain",
      "ispublic": 1,
      "isfriend": 0,
      "isfamily": 0
    },
    {
      "id": "55185482220",
      "owner": "143307536@N06",
      "secret": "7db4f1d114",
      "server": "65535",
      "farm": 66,
      "title": "Fire !",
      "ispublic": 1,
      "isfriend": 0,
      "isfamily": 0
    },
    {
      "id": "55185343780",
      "owner": "143307536@N06",
      "secret": "ec1d5b881b",
      "server": "65535",
      "farm": 66,
      "title": "Discuss",
      "ispublic": 1,
      "isfriend": 0,
      "isfamily": 0
    },
    {
      "id": "55183256418",
      "owner": "143307536@N06",
      "secret": "c85577be67",
      "server": "65535",
      "farm": 66,
      "title": "The ditch",
      "ispublic": 1,
      "isfriend": 0,
      "isfamily": 0
    },
    {
      "id": "55183023311",
      "owner": "143307536@N06",
      "secret": "24940c1efd",
      "server": "65535",
      "farm": 66,
      "title": "Medusa",
      "ispublic": 1,
      "isfriend": 0,
      "isfamily": 0
    },
    {
      "id": "55183181433",
      "owner": "143307536@N06",
      "secret": "79041a8bf3",
      "server": "65535",
      "farm": 66,
      "title": "Heart",
      "ispublic": 1,
      "isfriend": 0,
      "isfamily": 0
    },
    {
      "id": "55182148765",
      "owner": "143307536@N06",
      "secret": "e109595f24",
      "server": "65535",
      "farm": 66,
      "title": "Gold",
      "ispublic": 1,
      "isfriend": 0,
      "isfamily": 0
    },
    {
      "id": "55180429782",
      "owner": "143307536@N06",
      "secret": "dd2d34432c",
      "server": "65535",
      "farm": 66,
      "title": "the butcher",
      "ispublic": 1,
      "isfriend": 0,
      "isfamily": 0
    },
    {
      "id": "55181279184",
      "owner": "143307536@N06",
      "secret": "e9217d19ba",
      "server": "65535",
      "farm": 66,
      "title": "In the cage",
      "ispublic": 1,
      "isfriend": 0,
      "isfamily": 0
    },
    {
      "id": "55179317321",
      "owner": "143307536@N06",
      "secret": "f6c3629c2f",
      "server": "65535",
      "farm": 66,
      "title": "Man at work",
      "ispublic": 1,
      "isfriend": 0,
      "isfamily": 0
    },
    {
      "id": "55178017512",
      "owner": "143307536@N06",
      "secret": "6102206cb4",
      "server": "65535",
      "farm": 66,
      "title": "Executioner",
      "ispublic": 1,
      "isfriend": 0,
      "isfamily": 0
    },
    {
      "id": "55178899861",
      "owner": "143307536@N06",
      "secret": "4a6667e703",
      "server": "65535",
      "farm": 66,
      "title": "Hells Bells",
      "ispublic": 1,
      "isfriend": 0,
      "isfamily": 0
    },
    {
      "id": "55177603038",
      "owner": "143307536@N06",
      "secret": "aac5b1127f",
      "server": "65535",
      "farm": 66,
      "title": "Comics",
      "ispublic": 1,
      "isfriend": 0,
      "isfamily": 0
    },
    {
      "id": "55175890157",
      "owner": "143307536@N06",
      "secret": "d65211c3ea",
      "server": "65535",
      "farm": 66,
      "title": "The fight",
      "ispublic": 1,
      "isfriend": 0,
      "isfamily": 0
    },
    {
      "id": "55176907478",
      "owner": "143307536@N06",
      "secret": "41ac2417f7",
      "server": "65535",
      "farm": 66,
      "title": "Toilette",
      "ispublic": 1,
      "isfriend": 0,
      "isfamily": 0
    },
    {
      "id": "55175837082",
      "owner": "143307536@N06",
      "secret": "6f8c3c9192",
      "server": "65535",
      "farm": 66,
      "title": "Circe",
      "ispublic": 1,
      "isfriend": 0,
      "isfamily": 0
    },
    {
      "id": "55175459304",
      "owner": "143307536@N06",
      "secret": "966454110d",
      "server": "65535",
      "farm": 66,
      "title": "Sister",
      "ispublic": 1,
      "isfriend": 0,
      "isfamily": 0
    },
    {
      "id": "55175070890",
      "owner": "143307536@N06",
      "secret": "61922af66f",
      "server": "65535",
      "farm": 66,
      "title": "Evocation",
      "ispublic": 1,
      "isfriend": 0,
      "isfamily": 0
    },
    {
      "id": "55174759893",
      "owner": "143307536@N06",
      "secret": "fbe651b0d3",
      "server": "65535",
      "farm": 66,
      "title": "The kiss",
      "ispublic": 1,
      "isfriend": 0,
      "isfamily": 0
    },
    {
      "id": "55174517801",
      "owner": "143307536@N06",
      "secret": "341d0d2501",
      "server": "65535",
      "farm": 66,
      "title": "Anvil",
      "ispublic": 1,
      "isfriend": 0,
      "isfamily": 0
    },
    {
      "id": "55174514211",
      "owner": "143307536@N06",
      "secret": "098f0366fd",
      "server": "65535",
      "farm": 66,
      "title": "Cambodia",
      "ispublic": 1,
      "isfriend": 0,
      "isfamily": 0
    },
    {
      "id": "55174097574",
      "owner": "143307536@N06",
      "secret": "b5c15641d4",
      "server": "65535",
      "farm": 66,
      "title": "Monster",
      "ispublic": 1,
      "isfriend": 0,
      "isfamily": 0
    },
    {
      "id": "55172043987",
      "owner": "143307536@N06",
      "secret": "101d860eae",
      "server": "65535",
      "farm": 66,
      "title": "Recharge",
      "ispublic": 1,
      "isfriend": 0,
      "isfamily": 0
    },
    {
      "id": "55171947352",
      "owner": "143307536@N06",
      "secret": "34d9e8c36c",
      "server": "65535",
      "farm": 66,
      "title": "Gears",
      "ispublic": 1,
      "isfriend": 0,
      "isfamily": 0
    },
    {
      "id": "55173013104",
      "owner": "143307536@N06",
      "secret": "5e3779b86e",
      "server": "65535",
      "farm": 66,
      "title": "Submission",
      "ispublic": 1,
      "isfriend": 0,
      "isfamily": 0
    },
    {
      "id": "55173009734",
      "owner": "143307536@N06",
      "secret": "247c7567f1",
      "server": "65535",
      "farm": 66,
      "title": "Pitch",
      "ispublic": 1,
      "isfriend": 0,
      "isfamily": 0
    },
    {
      "id": "55171335549",
      "owner": "143307536@N06",
      "secret": "dac6655d58",
      "server": "65535",
      "farm": 66,
      "title": "Monnalisa",
      "ispublic": 1,
      "isfriend": 0,
      "isfamily": 0
    },
    {
      "id": "55171001921",
      "owner": "143307536@N06",
      "secret": "ff71b5a4a5",
      "server": "65535",
      "farm": 66,
      "title": "Rage",
      "ispublic": 1,
      "isfriend": 0,
      "isfamily": 0
    },
    {
      "id": "55171198289",
      "owner": "143307536@N06",
      "secret": "bdedb0bcdd",
      "server": "65535",
      "farm": 66,
      "title": "Divina",
      "ispublic": 1,
      "isfriend": 0,
      "isfamily": 0
    },
    {
      "id": "55168413192",
      "owner": "143307536@N06",
      "secret": "4296cf3f2a",
      "server": "65535",
      "farm": 66,
      "title": "Hybrid",
      "ispublic": 1,
      "isfriend": 0,
      "isfamily": 0
    },
    {
      "id": "55169541015",
      "owner": "143307536@N06",
      "secret": "6a0ba73885",
      "server": "65535",
      "farm": 66,
      "title": "the tongue",
      "ispublic": 1,
      "isfriend": 0,
      "isfamily": 0
    },
    {
      "id": "55168251737",
      "owner": "143307536@N06",
      "secret": "b293e09a58",
      "server": "65535",
      "farm": 66,
      "title": "the throne",
      "ispublic": 1,
      "isfriend": 0,
      "isfamily": 0
    },
    {
      "id": "55166643517",
      "owner": "143307536@N06",
      "secret": "0ce56455a8",
      "server": "65535",
      "farm": 66,
      "title": "Under construction",
      "ispublic": 1,
      "isfriend": 0,
      "isfamily": 0
    },
    {
      "id": "55167424576",
      "owner": "143307536@N06",
      "secret": "b0a2d5e03b",
      "server": "65535",
      "farm": 66,
      "title": "Apocalyptic",
      "ispublic": 1,
      "isfriend": 0,
      "isfamily": 0
    },
    {
      "id": "55166511702",
      "owner": "143307536@N06",
      "secret": "0434947505",
      "server": "65535",
      "farm": 66,
      "title": "Queen of sea",
      "ispublic": 1,
      "isfriend": 0,
      "isfamily": 0
    },
    {
      "id": "55167337711",
      "owner": "143307536@N06",
      "secret": "ea92015ac8",
      "server": "65535",
      "farm": 66,
      "title": "Sleep",
      "ispublic": 1,
      "isfriend": 0,
      "isfamily": 0
    },
    {
      "id": "55165374291",
      "owner": "143307536@N06",
      "secret": "b97ac0a223",
      "server": "65535",
      "farm": 66,
      "title": "Sentenced to beheading",
      "ispublic": 1,
      "isfriend": 0,
      "isfamily": 0
    },
    {
      "id": "55165619019",
      "owner": "143307536@N06",
      "secret": "3dee1d1464",
      "server": "65535",
      "farm": 66,
      "title": "Berber woman",
      "ispublic": 1,
      "isfriend": 0,
      "isfamily": 0
    },
    {
      "id": "55163699008",
      "owner": "143307536@N06",
      "secret": "a18316d110",
      "server": "65535",
      "farm": 66,
      "title": "NEW EXIBIT in Sadiana - \"Dystopian\"",
      "ispublic": 1,
      "isfriend": 0,
      "isfamily": 0
    },
    {
      "id": "55162633667",
      "owner": "143307536@N06",
      "secret": "8a84a5d22d",
      "server": "65535",
      "farm": 66,
      "title": "This is me",
      "ispublic": 1,
      "isfriend": 0,
      "isfamily": 0
    },
    {
      "id": "55163804515",
      "owner": "143307536@N06",
      "secret": "01bb736ca2",
      "server": "65535",
      "farm": 66,
      "title": "The green mile",
      "ispublic": 1,
      "isfriend": 0,
      "isfamily": 0
    },
    {
      "id": "55160473377",
      "owner": "143307536@N06",
      "secret": "111cfaf755",
      "server": "65535",
      "farm": 66,
      "title": "Checkmate",
      "ispublic": 1,
      "isfriend": 0,
      "isfamily": 0
    },
    {
      "id": "55161175316",
      "owner": "143307536@N06",
      "secret": "feb251aee2",
      "server": "65535",
      "farm": 66,
      "title": "Fobia",
      "ispublic": 1,
      "isfriend": 0,
      "isfamily": 0
    },
    {
      "id": "55158865367",
      "owner": "143307536@N06",
      "secret": "f408865a2a",
      "server": "65535",
      "farm": 66,
      "title": "Medusa",
      "ispublic": 1,
      "isfriend": 0,
      "isfamily": 0
    },
    {
      "id": "55159821090",
      "owner": "143307536@N06",
      "secret": "b04bf776ec",
      "server": "65535",
      "farm": 66,
      "title": "Watchdog",
      "ispublic": 1,
      "isfriend": 0,
      "isfamily": 0
    },
    {
      "id": "55159394726",
      "owner": "143307536@N06",
      "secret": "285212c811",
      "server": "65535",
      "farm": 66,
      "title": "Aliens",
      "ispublic": 1,
      "isfriend": 0,
      "isfamily": 0
    },
    {
      "id": "55158133485",
      "owner": "143307536@N06",
      "secret": "09e6de58a8",
      "server": "65535",
      "farm": 66,
      "title": "Dogs",
      "ispublic": 1,
      "isfriend": 0,
      "isfamily": 0
    },
    {
      "id": "55156846707",
      "owner": "143307536@N06",
      "secret": "80e830e9be",
      "server": "65535",
      "farm": 66,
      "title": "the horse",
      "ispublic": 1,
      "isfriend": 0,
      "isfamily": 0
    },
    {
      "id": "55156295954",
      "owner": "143307536@N06",
      "secret": "46b84d0c68",
      "server": "65535",
      "farm": 66,
      "title": "the church",
      "ispublic": 1,
      "isfriend": 0,
      "isfamily": 0
    },
    {
      "id": "55156144413",
      "owner": "143307536@N06",
      "secret": "40e077f26e",
      "server": "65535",
      "farm": 66,
      "title": "the strain",
      "ispublic": 1,
      "isfriend": 0,
      "isfamily": 0
    },
    {
      "id": "55154664235",
      "owner": "143307536@N06",
      "secret": "8408e045f9",
      "server": "65535",
      "farm": 66,
      "title": "Warrior",
      "ispublic": 1,
      "isfriend": 0,
      "isfamily": 0
    },
    {
      "id": "55154254056",
      "owner": "143307536@N06",
      "secret": "c07e389244",
      "server": "65535",
      "farm": 66,
      "title": "Afro gold",
      "ispublic": 1,
      "isfriend": 0,
      "isfamily": 0
    },
    {
      "id": "55154440664",
      "owner": "143307536@N06",
      "secret": "e3b3236190",
      "server": "65535",
      "farm": 66,
      "title": "Remake",
      "ispublic": 1,
      "isfriend": 0,
      "isfamily": 0
    },
    {
      "id": "55152819961",
      "owner": "143307536@N06",
      "secret": "6cab1658c8",
      "server": "65535",
      "farm": 66,
      "title": "Smeriglio",
      "ispublic": 1,
      "isfriend": 0,
      "isfamily": 0
    },
    {
      "id": "55151663337",
      "owner": "143307536@N06",
      "secret": "f552fba289",
      "server": "65535",
      "farm": 66,
      "title": "Red sea",
      "ispublic": 1,
      "isfriend": 0,
      "isfamily": 0
    },
    {
      "id": "55151522492",
      "owner": "143307536@N06",
      "secret": "4c7eabfea0",
      "server": "65535",
      "farm": 66,
      "title": "White devil",
      "ispublic": 1,
      "isfriend": 0,
      "isfamily": 0
    },
    {
      "id": "55151484883",
      "owner": "143307536@N06",
      "secret": "f7b010e318",
      "server": "65535",
      "farm": 66,
      "title": "Crow",
      "ispublic": 1,
      "isfriend": 0,
      "isfamily": 0
    },
    {
      "id": "55150430157",
      "owner": "143307536@N06",
      "secret": "89d45fa444",
      "server": "65535",
      "farm": 66,
      "title": "mask",
      "ispublic": 1,
      "isfriend": 0,
      "isfamily": 0
    },
    {
      "id": "55148475183",
      "owner": "143307536@N06",
      "secret": "d1f21d56fe",
      "server": "65535",
      "farm": 66,
      "title": "Tar",
      "ispublic": 1,
      "isfriend": 0,
      "isfamily": 0
    },
    {
      "id": "55147445239",
      "owner": "143307536@N06",
      "secret": "024a5304ed",
      "server": "65535",
      "farm": 66,
      "title": "Planet of the Apes",
      "ispublic": 1,
      "isfriend": 0,
      "isfamily": 0
    },
    {
      "id": "55146653656",
      "owner": "143307536@N06",
      "secret": "592fd8876e",
      "server": "65535",
      "farm": 66,
      "title": "NO WARS !",
      "ispublic": 1,
      "isfriend": 0,
      "isfamily": 0
    },
    {
      "id": "55146734043",
      "owner": "143307536@N06",
      "secret": "658e7a441b",
      "server": "65535",
      "farm": 66,
      "title": "Favola",
      "ispublic": 1,
      "isfriend": 0,
      "isfamily": 0
    },
    {
      "id": "55145172439",
      "owner": "143307536@N06",
      "secret": "c7d3e9183c",
      "server": "65535",
      "farm": 66,
      "title": "Do I deserve your submission?",
      "ispublic": 1,
      "isfriend": 0,
      "isfamily": 0
    },
    {
      "id": "55143997347",
      "owner": "143307536@N06",
      "secret": "770acb0484",
      "server": "65535",
      "farm": 66,
      "title": "Oriental nun",
      "ispublic": 1,
      "isfriend": 0,
      "isfamily": 0
    },
    {
      "id": "55144895306",
      "owner": "143307536@N06",
      "secret": "d94d581e33",
      "server": "65535",
      "farm": 66,
      "title": "A Master",
      "ispublic": 1,
      "isfriend": 0,
      "isfamily": 0
    },
    {
      "id": "55143574859",
      "owner": "143307536@N06",
      "secret": "19328135d3",
      "server": "65535",
      "farm": 66,
      "title": "Domina",
      "ispublic": 1,
      "isfriend": 0,
      "isfamily": 0
    },
    {
      "id": "55143312228",
      "owner": "143307536@N06",
      "secret": "31cceb9983",
      "server": "65535",
      "farm": 66,
      "title": "El Djablo",
      "ispublic": 1,
      "isfriend": 0,
      "isfamily": 0
    },
    {
      "id": "55141865734",
      "owner": "143307536@N06",
      "secret": "b58c25c626",
      "server": "65535",
      "farm": 66,
      "title": "Master",
      "ispublic": 1,
      "isfriend": 0,
      "isfamily": 0
    },
    {
      "id": "55142018145",
      "owner": "143307536@N06",
      "secret": "cf7df711b3",
      "server": "65535",
      "farm": 66,
      "title": "Matrix",
      "ispublic": 1,
      "isfriend": 0,
      "isfamily": 0
    },
    {
      "id": "55139774243",
      "owner": "143307536@N06",
      "secret": "fb03776df4",
      "server": "65535",
      "farm": 66,
      "title": "Wind",
      "ispublic": 1,
      "isfriend": 0,
      "isfamily": 0
    },
    {
      "id": "55139813249",
      "owner": "143307536@N06",
      "secret": "9751e8e78f",
      "server": "65535",
      "farm": 66,
      "title": "Dance in a volcano",
      "ispublic": 1,
      "isfriend": 0,
      "isfamily": 0
    },
    {
      "id": "55133561546",
      "owner": "143307536@N06",
      "secret": "c8908767a2",
      "server": "65535",
      "farm": 66,
      "title": "the altar",
      "ispublic": 1,
      "isfriend": 0,
      "isfamily": 0
    },
    {
      "id": "55132287010",
      "owner": "143307536@N06",
      "secret": "a4d5b6e207",
      "server": "65535",
      "farm": 66,
      "title": "Belle epoque (Variation)",
      "ispublic": 1,
      "isfriend": 0,
      "isfamily": 0
    },
    {
      "id": "55131819586",
      "owner": "143307536@N06",
      "secret": "742e442b94",
      "server": "65535",
      "farm": 66,
      "title": "Amazon",
      "ispublic": 1,
      "isfriend": 0,
      "isfamily": 0
    },
    {
      "id": "55128419618",
      "owner": "143307536@N06",
      "secret": "efa64897f1",
      "server": "65535",
      "farm": 66,
      "title": "Lamborghini",
      "ispublic": 1,
      "isfriend": 0,
      "isfamily": 0
    },
    {
      "id": "55115668590",
      "owner": "143307536@N06",
      "secret": "2b1628e911",
      "server": "65535",
      "farm": 66,
      "title": "Horse",
      "ispublic": 1,
      "isfriend": 0,
      "isfamily": 0
    },
    {
      "id": "55112521265",
      "owner": "143307536@N06",
      "secret": "150f4ae520",
      "server": "65535",
      "farm": 66,
      "title": "Loosing my religion",
      "ispublic": 1,
      "isfriend": 0,
      "isfamily": 0
    },
    {
      "id": "55111776500",
      "owner": "143307536@N06",
      "secret": "7a3cf751d7",
      "server": "65535",
      "farm": 66,
      "title": "Sphere",
      "ispublic": 1,
      "isfriend": 0,
      "isfamily": 0
    },
    {
      "id": "55109624675",
      "owner": "143307536@N06",
      "secret": "71d0e0c170",
      "server": "65535",
      "farm": 66,
      "title": "Punkslave",
      "ispublic": 1,
      "isfriend": 0,
      "isfamily": 0
    },
    {
      "id": "53434962591",
      "owner": "143307536@N06",
      "secret": "db4f46f07f",
      "server": "65535",
      "farm": 66,
      "title": "Retrò",
      "ispublic": 1,
      "isfriend": 0,
      "isfamily": 0
    },
    {
      "id": "51564973610",
      "owner": "143307536@N06",
      "secret": "73d09a8165",
      "server": "65535",
      "farm": 66,
      "title": "Nera",
      "ispublic": 1,
      "isfriend": 0,
      "isfamily": 0
    },
    {
      "id": "51497012800",
      "owner": "143307536@N06",
      "secret": "9b157c2113",
      "server": "65535",
      "farm": 66,
      "title": "King of flower",
      "ispublic": 1,
      "isfriend": 0,
      "isfamily": 0
    },
    {
      "id": "51490719877",
      "owner": "143307536@N06",
      "secret": "e057453787",
      "server": "65535",
      "farm": 66,
      "title": "jack of spade",
      "ispublic": 1,
      "isfriend": 0,
      "isfamily": 0
    },
    {
      "id": "51398418167",
      "owner": "143307536@N06",
      "secret": "96c80820fa",
      "server": "65535",
      "farm": 66,
      "title": "Cyber Master",
      "ispublic": 1,
      "isfriend": 0,
      "isfamily": 0
    },
    {
      "id": "50855387233",
      "owner": "143307536@N06",
      "secret": "1dc7183969",
      "server": "65535",
      "farm": 66,
      "title": "Djablo master",
      "ispublic": 1,
      "isfriend": 0,
      "isfamily": 0
    },
    {
      "id": "48773875386",
      "owner": "143307536@N06",
      "secret": "74a55a5f4d",
      "server": "65535",
      "farm": 66,
      "title": "Santorini",
      "ispublic": 1,
      "isfriend": 0,
      "isfamily": 0
    },
    {
      "id": "48738500121",
      "owner": "143307536@N06",
      "secret": "82b798f424",
      "server": "65535",
      "farm": 66,
      "title": "Red & white",
      "ispublic": 1,
      "isfriend": 0,
      "isfamily": 0
    },
    {
      "id": "47597857991",
      "owner": "143307536@N06",
      "secret": "01e6576921",
      "server": "7844",
      "farm": 8,
      "title": "Vent",
      "ispublic": 1,
      "isfriend": 0,
      "isfamily": 0
    },
    {
      "id": "46682183125",
      "owner": "143307536@N06",
      "secret": "b36f67f6d6",
      "server": "7801",
      "farm": 8,
      "title": "FLOU",
      "ispublic": 1,
      "isfriend": 0,
      "isfamily": 0
    },
    {
      "id": "33687582458",
      "owner": "143307536@N06",
      "secret": "8689b147f3",
      "server": "7889",
      "farm": 8,
      "title": "Sea-&-Rain",
      "ispublic": 1,
      "isfriend": 0,
      "isfamily": 0
    },
    {
      "id": "33672960198",
      "owner": "143307536@N06",
      "secret": "0d779ba430",
      "server": "7837",
      "farm": 8,
      "title": "Thoughts",
      "ispublic": 1,
      "isfriend": 0,
      "isfamily": 0
    },
    {
      "id": "35433513400",
      "owner": "143307536@N06",
      "secret": "dd071ef762",
      "server": "4266",
      "farm": 5,
      "title": "Flowers",
      "ispublic": 1,
      "isfriend": 0,
      "isfamily": 0
    },
    {
      "id": "34893104184",
      "owner": "143307536@N06",
      "secret": "7dc2092995",
      "server": "4279",
      "farm": 5,
      "title": "Master",
      "ispublic": 1,
      "isfriend": 0,
      "isfamily": 0
    },
    {
      "id": "33115248853",
      "owner": "143307536@N06",
      "secret": "6cce32854c",
      "server": "3956",
      "farm": 4,
      "title": "Mystique",
      "ispublic": 1,
      "isfriend": 0,
      "isfamily": 0
    },
    {
      "id": "32990576324",
      "owner": "143307536@N06",
      "secret": "a7fe99c90a",
      "server": "3955",
      "farm": 4,
      "title": "Indiana",
      "ispublic": 1,
      "isfriend": 0,
      "isfamily": 0
    },
    {
      "id": "29870473110",
      "owner": "143307536@N06",
      "secret": "402c38c297",
      "server": "5107",
      "farm": 6,
      "title": "Aglaia",
      "ispublic": 1,
      "isfriend": 0,
      "isfamily": 0
    },
    {
      "id": "29520987144",
      "owner": "143307536@N06",
      "secret": "3b1f121f07",
      "server": "5623",
      "farm": 6,
      "title": "Scent",
      "ispublic": 1,
      "isfriend": 0,
      "isfamily": 0
    },
    {
      "id": "29603711725",
      "owner": "143307536@N06",
      "secret": "5b78a8336d",
      "server": "8228",
      "farm": 9,
      "title": "Crows",
      "ispublic": 1,
      "isfriend": 0,
      "isfamily": 0
    }
  ]
}